gtec_pp/__init__.py
gtec_pp/__version__.py
gtec_pp/paradigm_presenter.py
gtec_pp/imp/pplib.cp38-win_amd64.pyd
gtec_pp-1.1.1.dist-info/LICENSE
gtec_pp-1.1.1.dist-info/METADATA
gtec_pp-1.1.1.dist-info/WHEEL
gtec_pp-1.1.1.dist-info/top_level.txt
gtec_pp-1.1.1.dist-info/RECORD
