Metadata-Version: 2.1
Name: gtec-pp
Version: 1.1.1
Summary: Paradigm Presenter Python API
Home-page: https://www.gtec.at
Author: g.tec medical engineering GmbH
Author-email: support@gtec.at
License: g.tec Non-Commercial License (GNCL)
Classifier: Development Status :: 3 - Alpha
Classifier: Operating System :: OS Independent
Classifier: Programming Language :: Python :: 3
License-File: LICENSE
